vaulthelpers/__init__.py
vaulthelpers/aws.py
vaulthelpers/common.py
vaulthelpers/database.py
vaulthelpers/exceptions.py
vaulthelpers/storage.py
vaulthelpers/utils.py
vaulthelpers/management/__init__.py
vaulthelpers/management/commands/__init__.py
vaulthelpers/management/commands/revoke_vault_leases.py
vaulthelpers/tests/__init__.py
vaulthelpers/tests/base.py
vaulthelpers/tests/test_authentication.py
vaulthelpers/tests/test_aws.py
vaulthelpers/tests/test_config.py
vaulthelpers/tests/test_database.py
django_vault_helpers-0.8.1.dist-info/LICENSE
django_vault_helpers-0.8.1.dist-info/METADATA
django_vault_helpers-0.8.1.dist-info/WHEEL
django_vault_helpers-0.8.1.dist-info/top_level.txt
django_vault_helpers-0.8.1.dist-info/RECORD
