Metadata-Version: 2.1
Name: django-vault-helpers
Version: 0.8.1
Summary: Helper functionality for obtaining secrets and credentials from Hashicorp Vault in a Django project
Home-page: https://gitlab.com/thelabnyc/django-vault-helpers
Author: Craig Weber
Author-email: crgwbr@gmail.com
License: ISC
Platform: UNKNOWN
Classifier: Development Status :: 5 - Production/Stable
Classifier: Environment :: Console
Classifier: Environment :: Web Environment
Classifier: Framework :: Django
Classifier: Framework :: Django :: 1.11
Classifier: Framework :: Django :: 2.0
Classifier: Intended Audience :: Developers
Classifier: License :: OSI Approved :: ISC License (ISCL)
Classifier: Operating System :: Unix
Classifier: Operating System :: MacOS :: MacOS X
Classifier: Programming Language :: Python
Classifier: Programming Language :: Python :: 3
Classifier: Programming Language :: Python :: 3.4
Classifier: Programming Language :: Python :: 3.5
Classifier: Programming Language :: Python :: 3.6
Requires-Dist: Django (>=1.11)
Requires-Dist: hvac (>=0.3.0)
Requires-Dist: portalocker (>=1.1.0)
Requires-Dist: pytz (>=2017.2)
Requires-Dist: python-dateutil (>=2.6.1)
Provides-Extra: aws
Requires-Dist: boto3 (>=1.4.7) ; extra == 'aws'
Requires-Dist: botocore (>=1.7.22) ; extra == 'aws'
Provides-Extra: database
Requires-Dist: dj-database-url (>=0.4.2) ; extra == 'database'
Provides-Extra: development
Requires-Dist: flake8 (>=3.3.0) ; extra == 'development'
Requires-Dist: freezegun (>=0.3.9) ; extra == 'development'
Requires-Dist: psycopg2-binary (>=2.7.1) ; extra == 'development'
Requires-Dist: requests-mock (>=1.4.0) ; extra == 'development'
Requires-Dist: tox (>=2.7.0) ; extra == 'development'
Requires-Dist: versiontag (>=1.2.0) ; extra == 'development'
Provides-Extra: sentry
Requires-Dist: sentry-sdk (>=0.5.5) ; extra == 'sentry'
